{
  "recentFiles": [
    {
      "basename": "未命名 1",
      "path": "游戏开发/游戏案例分析/未命名 1.md"
    },
    {
      "basename": "Drawing 2023-10-26 17.29.31.excalidraw",
      "path": "Excalidraw/Drawing 2023-10-26 17.29.31.excalidraw.md"
    },
    {
      "basename": "《辐射》",
      "path": "游戏开发/游戏案例分析/《辐射》.md"
    },
    {
      "basename": "《质量效应》三部曲",
      "path": "游戏开发/游戏案例分析/《质量效应》三部曲.md"
    },
    {
      "basename": "调酒游戏",
      "path": "灵感/灵感memo/调酒游戏.md"
    },
    {
      "basename": "《GTA》",
      "path": "游戏开发/游戏案例分析/《GTA》.md"
    },
    {
      "basename": "二游《绯色回响》",
      "path": "游戏开发/游戏案例分析/二游《绯色回响》.md"
    },
    {
      "basename": "游戏乐趣",
      "path": "游戏开发/游戏设计课程/游戏乐趣.md"
    },
    {
      "basename": "pic_游戏乐趣1",
      "path": "游戏开发/游戏设计课程/pic_游戏乐趣1.png"
    },
    {
      "basename": "2310吉比特GameJam团队总结",
      "path": "游戏开发/Gamejam/2310吉比特/2310吉比特GameJam团队总结.md"
    },
    {
      "basename": "Pasted image 20231031022838",
      "path": "游戏开发/Gamejam/2310吉比特/Pasted image 20231031022838.png"
    },
    {
      "basename": "Pasted image 20231031023218",
      "path": "游戏开发/Gamejam/2310吉比特/Pasted image 20231031023218.png"
    },
    {
      "basename": "Pasted image 20231031023758",
      "path": "游戏开发/Gamejam/2310吉比特/Pasted image 20231031023758.png"
    },
    {
      "basename": "2310吉比特GameJam策划总结",
      "path": "游戏开发/Gamejam/2310吉比特/2310吉比特GameJam策划总结.md"
    },
    {
      "basename": "游戏机制",
      "path": "游戏开发/游戏设计课程/游戏机制.md"
    },
    {
      "basename": "2310布谷GameJam策划总结",
      "path": "游戏开发/Gamejam/2310布谷GameJam/2310布谷GameJam策划总结.md"
    },
    {
      "basename": "2310布谷GameJam团队总结",
      "path": "游戏开发/Gamejam/2310布谷GameJam/2310布谷GameJam团队总结.md"
    },
    {
      "basename": "GMTK2021-主题《Joined Together》",
      "path": "游戏开发/GMTK笔记/GMTK2021-主题《Joined Together》.md"
    },
    {
      "basename": "GMTK2020-主题《Out of Control》",
      "path": "游戏开发/GMTK笔记/GMTK2020-主题《Out of Control》.md"
    },
    {
      "basename": "GMTK2019-主题《only one》",
      "path": "游戏开发/GMTK笔记/GMTK2019-主题《only one》.md"
    },
    {
      "basename": "GMTK2023-主题《Roles reversed》",
      "path": "游戏开发/GMTK笔记/GMTK2023-主题《Roles reversed》.md"
    },
    {
      "basename": "GMTK2022-主题《Roll of the Dice》",
      "path": "游戏开发/GMTK笔记/GMTK2022-主题《Roll of the Dice》.md"
    },
    {
      "basename": "灵感散记",
      "path": "灵感/灵感散记.md"
    },
    {
      "basename": "Pasted image 20231026215809",
      "path": "游戏开发/GMTK笔记/GMTK游戏截图/GMTK2020/Pasted image 20231026215809.png"
    },
    {
      "basename": "Pasted image 20231026215700",
      "path": "游戏开发/GMTK笔记/GMTK游戏截图/GMTK2020/Pasted image 20231026215700.png"
    },
    {
      "basename": "Pasted image 20231026185117",
      "path": "游戏开发/GMTK笔记/GMTK游戏截图/GMTK2020/Pasted image 20231026185117.png"
    },
    {
      "basename": "sortspec",
      "path": "obsidian使用相关/sortspec.md"
    },
    {
      "basename": "2023-10-26",
      "path": "日记/2023-10-26.md"
    },
    {
      "basename": "日记模板1",
      "path": "obsidian使用相关/templater/日记模板1.md"
    },
    {
      "basename": "灵感模板1",
      "path": "obsidian使用相关/templater/灵感模板1.md"
    }
  ],
  "omittedPaths": [],
  "maxLength": null,
  "openType": "tab"
}